<?xml version="1.0" encoding="UTF-8"?>
<!-- Example of a simple "odf" structure for a refrigerator. -->
<Objects xmlns:xsi="http://www.w3.org/2001/XMLSchema-instance" xsi:noNamespaceSchemaLocation="odf.xsd">
    <Object type="Refrigerator Assembly Product">
        <id>SmartFridge22334411</id>
        <InfoItem udef="b.o.9_1.1.14.13" id="Consumed Electrical Power Measure">
            <description>Power consumption values with timestamp.</description>
            <value dateTime="2001-10-26T15:33:21">15.5</value>
            <value dateTime="2001-10-26T15:33:50">15.7</value>
            <value dateTime="2001-10-26T15:34:15">1.3</value>
            <value dateTime="2001-10-26T15:34:35">1.5</value>
            <value dateTime="2001-10-26T15:34:52">15.3</value>
        </InfoItem>
    </Object>
</Objects>
